Metadata-Version: 1.0
Name: nicwaller.yq
Version: 0.1.2
Summary: A little wrapper for jq to read YAML files
Home-page: https://github.com/nicwaller/yq
Author: Nic Waller
Author-email: code@nicwaller.com
License: UNKNOWN
Platform: UNKNOWN
